README.md
setup.cfg
setup.py
pyTelegramWalletApi.egg-info/PKG-INFO
pyTelegramWalletApi.egg-info/SOURCES.txt
pyTelegramWalletApi.egg-info/dependency_links.txt
pyTelegramWalletApi.egg-info/requires.txt
pyTelegramWalletApi.egg-info/top_level.txt
tests/__init__.py
tests/test_account.py
tests/test_p2p.py
tests/utils.py
wallet/__init__.py
wallet/web_client.py
wallet/rest/__init__.py
wallet/types/__init__.py
wallet/types/balances.py
wallet/types/offers.py
wallet/types/transactions.py