Metadata-Version: 2.1
Name: pyTelegramWalletApi
Version: 0.2.34
Summary: Telegram Wallet API
Author: no-name-user-name
Author-email: dimazver61@gmail.com
